{"version": 0.6, "generator": "Overpass API 0.7.62.7 375dc00a", "osm3s": {"timestamp_osm_base": "2025-06-14T14:47:30Z", "copyright": "The data included in this document is from www.openstreetmap.org. The data is made available under ODbL."}, "elements": [{"type": "node", "id": 7853189885, "lat": 39.5400853, "lon": 24.9884477, "tags": {"amenity": "restaurant", "cuisine": "greek", "internet_access": "wlan", "name": "\u03a4\u03b1\u03b2\u03ad\u03c1\u03bd\u03b1 \"\u0392\u03b5\u03c1\u03ac\u03bd\u03c4\u03b1\"", "name:el": "\u03a4\u03b1\u03b2\u03ad\u03c1\u03bd\u03b1 \"\u0392\u03b5\u03c1\u03ac\u03bd\u03c4\u03b1\"", "name:en": "Restaurant \"Veranta\""}}, {"type": "node", "id": 7859374685, "lat": 39.5397511, "lon": 24.9882795, "tags": {"amenity": "restaurant", "cuisine": "greek", "internet_access": "wlan", "name": "\u03a4\u03b1\u03b2\u03ad\u03c1\u03bd\u03b1 \"\u0391\u03c1\u03c4\u03b5\u03bc\u03c9\u03bd\u03b1\u03c2\"", "name:el": "\u03a4\u03b1\u03b2\u03ad\u03c1\u03bd\u03b1 \"\u0391\u03c1\u03c4\u03b5\u03bc\u03c9\u03bd\u03b1\u03c2\"", "name:en": "Restaurant \"Artemonas\""}}, {"type": "node", "id": 7859374686, "lat": 39.5396739, "lon": 24.988435, "tags": {"amenity": "cafe", "cuisine": "coffee_shop;crepe", "internet_access": "wlan", "name": "Jimmy's Cafe"}}]}