{"version": 0.6, "generator": "Overpass API 0.7.62.7 375dc00a", "osm3s": {"timestamp_osm_base": "2025-06-14T15:35:24Z", "copyright": "The data included in this document is from www.openstreetmap.org. The data is made available under ODbL."}, "elements": [{"type": "node", "id": 4112553962, "lat": 29.9614289, "lon": 40.2221339}, {"type": "node", "id": 4112553963, "lat": 29.9613106, "lon": 40.2221461}, {"type": "node", "id": 4112553964, "lat": 29.9612999, "lon": 40.2220085}, {"type": "node", "id": 4112553965, "lat": 29.9614182, "lon": 40.2219963}, {"type": "node", "id": 4112553966, "lat": 29.9639821, "lon": 40.1962636, "tags": {"amenity": "restaurant", "cuisine": "regional", "name": "Kudu"}}, {"type": "node", "id": 4731173826, "lat": 29.9331904, "lon": 40.1876159, "tags": {"amenity": "restaurant", "name": "\u0647\u0631\u0641\u064a", "name:ar": "\u0647\u0631\u0641\u064a", "name:en": "herfy"}}, {"type": "node", "id": 4731184923, "lat": 29.9324013, "lon": 40.1866155, "tags": {"amenity": "restaurant", "name": "\u0627\u0644\u0637\u0627\u0632\u062c", "name:ar": "\u0627\u0644\u0637\u0627\u0632\u062c"}}, {"type": "node", "id": 5602132721, "lat": 29.9722873, "lon": 40.1986077, "tags": {"addr:street": "\u0627\u0644\u0645\u0644\u0643 \u0633\u0639\u0648\u062f", "amenity": "restaurant", "cuisine": "friture", "name": "\u0645\u0637\u0639\u0645 \u0647\u0631\u0641\u064a"}}, {"type": "node", "id": 5838718899, "lat": 29.8085211, "lon": 39.9070725}, {"type": "node", "id": 5838718900, "lat": 29.8083682, "lon": 39.9069092}, {"type": "node", "id": 5838718901, "lat": 29.8081743, "lon": 39.9071734}, {"type": "node", "id": 5838718902, "lat": 29.8083347, "lon": 39.9073346}, {"type": "node", "id": 6093199085, "lat": 29.9592203, "lon": 40.2045316, "tags": {"amenity": "restaurant", "name": "\u0645\u0627\u0643\u062f\u0648\u0646\u0627\u0644\u062f\u0632"}}, {"type": "node", "id": 10159027240, "lat": 29.9699887, "lon": 40.2231895, "tags": {"amenity": "cafe", "name": "\u062f\u0627\u0646\u0643\u0646 \u062f\u0648\u0646\u0627\u062a"}}, {"type": "node", "id": 10159027243, "lat": 29.9850272, "lon": 40.2157697, "tags": {"addr:city": "\u0633\u0643\u0627\u0643\u0627", "addr:neighbourhood": "\u0627\u0644\u0634\u0639\u064a\u0628", "amenity": "restaurant", "name": "\u0645\u0637\u0639\u0645 \u0627\u0644\u0646\u0627\u0641\u0648\u0631\u0629"}}, {"type": "node", "id": 10162262315, "lat": 29.9600217, "lon": 40.2078342, "tags": {"amenity": "restaurant", "name": "\u0628\u064a\u062a \u0627\u0644\u0634\u0648\u0627\u064a\u0629"}}, {"type": "node", "id": 10162300228, "lat": 29.9644375, "lon": 40.2218795, "tags": {"amenity": "restaurant", "name": "\u062d\u0627\u0634\u064a \u0628\u0627\u0634\u0627"}}, {"type": "node", "id": 10216779122, "lat": 29.9467709, "lon": 40.2258918, "tags": {"amenity": "restaurant", "name": "\u062a\u0631\u0627\u062b \u0627\u0644\u062c\u0648\u0641"}}, {"type": "node", "id": 10219512429, "lat": 29.9591373, "lon": 40.2050833, "tags": {"amenity": "restaurant", "cuisine": "pizza", "name": "\u062f\u0648\u0645\u064a\u0646\u0648\u0632 \u0628\u064a\u062a\u0632\u0627"}}, {"type": "node", "id": 10219512601, "lat": 29.9591764, "lon": 40.2054238, "tags": {"amenity": "restaurant", "cuisine": "pizza", "name": "\u0645\u064a\u0633\u062a\u0631\u0648"}}, {"type": "node", "id": 10220115947, "lat": 29.9790106, "lon": 40.1856365, "tags": {"amenity": "restaurant", "name": "\u0641\u0631\u0633\u0627\u0646 \u0627\u0644\u0634\u0627\u0645"}}, {"type": "node", "id": 10220115978, "lat": 29.979622, "lon": 40.1831763, "tags": {"amenity": "cafe", "name": "\u0639\u0646\u0648\u0627\u0646 \u0627\u0644\u0642\u0647\u0648\u0629"}}, {"type": "node", "id": 10235226782, "lat": 29.9585984, "lon": 40.2069479, "tags": {"amenity": "restaurant", "name": "\u0642\u0635\u0631 \u0627\u0644\u0639\u064a\u0634\u0627\u0646 \u0627\u0644\u062a\u0631\u0627\u062b\u064a"}}, {"type": "node", "id": 10235843187, "lat": 29.959102, "lon": 40.2064272, "tags": {"amenity": "restaurant", "name": "\u0634\u0627\u0648\u0631\u0645\u0627 \u0644\u0627\u064a\u0641"}}, {"type": "node", "id": 10236757575, "lat": 29.9323377, "lon": 40.1863535, "tags": {"amenity": "restaurant", "cuisine": "pizza", "name": "\u0644\u064a\u062a\u0631\u0633\u064a\u0632\u0631"}}, {"type": "node", "id": 10240338891, "lat": 29.9721514, "lon": 40.1885083, "tags": {"amenity": "restaurant", "name": "\u0643\u0648\u0632\u0648"}}, {"type": "node", "id": 10242122892, "lat": 29.9764669, "lon": 40.1903018, "tags": {"amenity": "cafe", "name": "CH"}}, {"type": "node", "id": 10242122917, "lat": 29.9506058, "lon": 40.1887642, "tags": {"amenity": "cafe", "name": "\u0641\u0644 \u0633\u062a\u0648\u0628"}}, {"type": "node", "id": 10242231811, "lat": 29.9780537, "lon": 40.204187, "tags": {"amenity": "restaurant", "name": "\u0644\u0624\u0644\u0648\u0629 \u0627\u0644\u062c\u0648\u0641"}}, {"type": "node", "id": 10242231816, "lat": 29.966436, "lon": 40.2154225, "tags": {"amenity": "restaurant", "name": "\u0627\u0644\u0627\u062d\u0644\u0627\u0645"}}, {"type": "node", "id": 10242231836, "lat": 29.9735393, "lon": 40.1997734, "tags": {"amenity": "cafe", "name": "Elm"}}, {"type": "node", "id": 10242231842, "lat": 29.9777682, "lon": 40.2034281, "tags": {"amenity": "restaurant", "name": "\u0644\u064a\u0627\u0644\u064a \u0627\u0644\u0634\u0627\u0645"}}, {"type": "node", "id": 10242361920, "lat": 29.9935974, "lon": 40.2091128, "tags": {"amenity": "cafe", "name": "\u0644\u0641\u064a\u062f\u0627"}}, {"type": "node", "id": 10242368609, "lat": 29.9894147, "lon": 40.2137809, "tags": {"amenity": "restaurant", "name": "\u0627\u0644\u0648\u0637\u0646\u064a"}}, {"type": "node", "id": 10242870431, "lat": 29.9997154, "lon": 40.2112294, "tags": {"amenity": "restaurant", "name": "\u0627\u0644\u0628\u0631\u0643\u0629"}}, {"type": "node", "id": 10244013922, "lat": 29.9956349, "lon": 40.2090886, "tags": {"amenity": "restaurant", "name": "\u0634\u064a\u0643\u0627\u0646\u062f\u064a"}}, {"type": "node", "id": 10244013925, "lat": 29.9959753, "lon": 40.2091854, "tags": {"amenity": "restaurant", "name": "\u0641\u0631\u0633\u0627\u0646 \u0627\u0644\u0634\u0627\u0645"}}, {"type": "node", "id": 10244013926, "lat": 29.9950782, "lon": 40.2091155, "tags": {"amenity": "restaurant", "name": "\u0633\u0631\u0627\u064a\u0627"}}, {"type": "node", "id": 10244069379, "lat": 29.9553687, "lon": 40.1901278, "tags": {"amenity": "cafe", "name": "\u0627\u0637\u0644\u0627\u0644\u0629 \u0627\u0644\u0634\u0627\u064a"}}, {"type": "node", "id": 10246542917, "lat": 29.9747806, "lon": 40.1903256, "tags": {"air_conditioning": "yes", "amenity": "restaurant", "name": "\u0645\u0633\u062a\u0631 \u0639\u0646\u0628"}}, {"type": "node", "id": 10246542918, "lat": 29.9747043, "lon": 40.1903064, "tags": {"amenity": "restaurant", "name": "\u0627\u0644\u062a\u0646\u0648\u0631"}}, {"type": "way", "id": 409342196, "nodes": [4112553962, 4112553963, 4112553964, 4112553965, 4112553962], "tags": {"amenity": "restaurant", "building": "yes", "cuisine": "regional", "name": "Kudu", "not:brand:wikidata": "Q6441777"}}, {"type": "way", "id": 617674554, "nodes": [5838718899, 5838718900, 5838718901, 5838718902, 5838718899], "tags": {"amenity": "restaurant", "building": "yes"}}]}