{"version": 0.6, "generator": "Overpass API 0.7.62.7 375dc00a", "osm3s": {"timestamp_osm_base": "2025-06-14T13:50:30Z", "copyright": "The data included in this document is from www.openstreetmap.org. The data is made available under ODbL."}, "elements": [{"type": "node", "id": 7869756285, "lat": 35.8621334, "lon": 12.8542233, "tags": {"amenity": "restaurant", "name": "The Black Planet"}}, {"type": "node", "id": 7872145187, "lat": 35.8598893, "lon": 12.8635759, "tags": {"amenity": "restaurant", "cuisine": "pasta;fish;chicken;regional", "name": "Anciuluzzu food Cruderie di pesce", "outdoor_seating": "yes", "takeaway": "yes"}}]}